{
  "DLSVersion": "2.1.6",
  "Name": "8 bit offsetter",
  "NameLocation": 0,
  "ChipType": 0,
  "Size": {
    "x": 1.7,
    "y": 1.25
  },
  "Colour": {
    "r": 0.226254329,
    "g": 0.2855133,
    "b": 0.149798214,
    "a": 1
  },
  "InputPins":[
    {
      "Name":"Write",
      "ID":137033583,
      "Position":{
        "x":-12.62126,
        "y":2.06634
      },
      "BitCount":1,
      "Colour":0,
      "ValueDisplayMode":0
    },
    {
      "Name":"Clock",
      "ID":1446028969,
      "Position":{
        "x":-12.93546,
        "y":1.23916
      },
      "BitCount":1,
      "Colour":0,
      "ValueDisplayMode":0
    },
    {
      "Name":"reset",
      "ID":1228957957,
      "Position":{
        "x":-12.93546,
        "y":0.73442
      },
      "BitCount":1,
      "Colour":0,
      "ValueDisplayMode":0
    },
    {
      "Name":"IN",
      "ID":1975419030,
      "Position":{
        "x":-11.74451,
        "y":-0.29295
      },
      "BitCount":8,
      "Colour":0,
      "ValueDisplayMode":2
    }
  ],
  "OutputPins":[
    {
      "Name":"OUT",
      "ID":200910699,
      "Position":{
        "x":5.49891,
        "y":5.39855
      },
      "BitCount":8,
      "Colour":0,
      "ValueDisplayMode":1
    }
  ],
  "SubChips":[
    {
      "Name":"add 8",
      "ID":200770344,
      "Label":"",
      "Position":{
        "x":-6.78449,
        "y":2.69326
      },
      "OutputPinColourInfo":[{"PinColour":0,"PinID":26672147},{"PinColour":0,"PinID":1993145858}],
      "InternalData":null
    },
    {
      "Name":"8 bit register",
      "ID":1225851529,
      "Label":"",
      "Position":{
        "x":-2.89576,
        "y":1.83615
      },
      "OutputPinColourInfo":[{"PinColour":0,"PinID":1562396775}],
      "InternalData":null
    },
    {
      "Name":"8 bit register",
      "ID":949796810,
      "Label":"",
      "Position":{
        "x":-1.1395,
        "y":4.25828
      },
      "OutputPinColourInfo":[{"PinColour":0,"PinID":1562396775}],
      "InternalData":null
    },
    {
      "Name":"NOT",
      "ID":605526266,
      "Label":"",
      "Position":{
        "x":-4.83365,
        "y":3.8862
      },
      "OutputPinColourInfo":[{"PinColour":0,"PinID":855358909}],
      "InternalData":null
    }
  ],
  "Wires":[
    {
      "SourcePinAddress":{
        "PinID":1993145858,
        "PinOwnerID":200770344
      },
      "TargetPinAddress":{
        "PinID":2035711096,
        "PinOwnerID":1225851529
      },
      "ConnectionType":0,
      "ConnectedWireIndex":-1,
      "ConnectedWireSegmentIndex":-1,
      "Points":[{"x":0.0,"y":0.0},{"x":0.0,"y":0.0}]
    },
    {
      "SourcePinAddress":{
        "PinID":0,
        "PinOwnerID":1975419030
      },
      "TargetPinAddress":{
        "PinID":1634636466,
        "PinOwnerID":200770344
      },
      "ConnectionType":0,
      "ConnectedWireIndex":-1,
      "ConnectedWireSegmentIndex":-1,
      "Points":[{"x":0.0,"y":0.0},{"x":-10.63734,"y":2.6806},{"x":0.0,"y":0.0}]
    },
    {
      "SourcePinAddress":{
        "PinID":0,
        "PinOwnerID":1228957957
      },
      "TargetPinAddress":{
        "PinID":666811291,
        "PinOwnerID":1225851529
      },
      "ConnectionType":0,
      "ConnectedWireIndex":-1,
      "ConnectedWireSegmentIndex":-1,
      "Points":[{"x":0.0,"y":0.0},{"x":0.0,"y":0.0}]
    },
    {
      "SourcePinAddress":{
        "PinID":0,
        "PinOwnerID":1446028969
      },
      "TargetPinAddress":{
        "PinID":1799399034,
        "PinOwnerID":1225851529
      },
      "ConnectionType":0,
      "ConnectedWireIndex":-1,
      "ConnectedWireSegmentIndex":-1,
      "Points":[{"x":0.0,"y":0.0},{"x":0.0,"y":0.0}]
    },
    {
      "SourcePinAddress":{
        "PinID":0,
        "PinOwnerID":137033583
      },
      "TargetPinAddress":{
        "PinID":1056611029,
        "PinOwnerID":1225851529
      },
      "ConnectionType":0,
      "ConnectedWireIndex":-1,
      "ConnectedWireSegmentIndex":-1,
      "Points":[{"x":0.0,"y":0.0},{"x":0.0,"y":0.0}]
    },
    {
      "SourcePinAddress":{
        "PinID":0,
        "PinOwnerID":1228957957
      },
      "TargetPinAddress":{
        "PinID":666811291,
        "PinOwnerID":949796810
      },
      "ConnectionType":1,
      "ConnectedWireIndex":2,
      "ConnectedWireSegmentIndex":0,
      "Points":[{"x":-7.1295,"y":1.08902},{"x":0.0,"y":0.0}]
    },
    {
      "SourcePinAddress":{
        "PinID":1562396775,
        "PinOwnerID":1225851529
      },
      "TargetPinAddress":{
        "PinID":2035711096,
        "PinOwnerID":949796810
      },
      "ConnectionType":0,
      "ConnectedWireIndex":-1,
      "ConnectedWireSegmentIndex":-1,
      "Points":[{"x":0.0,"y":0.0},{"x":-1.40571,"y":2.19418},{"x":-3.3808,"y":4.21398},{"x":0.0,"y":0.0}]
    },
    {
      "SourcePinAddress":{
        "PinID":855358909,
        "PinOwnerID":605526266
      },
      "TargetPinAddress":{
        "PinID":1056611029,
        "PinOwnerID":949796810
      },
      "ConnectionType":0,
      "ConnectedWireIndex":-1,
      "ConnectedWireSegmentIndex":-1,
      "Points":[{"x":0.0,"y":0.0},{"x":0.0,"y":0.0}]
    },
    {
      "SourcePinAddress":{
        "PinID":0,
        "PinOwnerID":1446028969
      },
      "TargetPinAddress":{
        "PinID":2032820543,
        "PinOwnerID":605526266
      },
      "ConnectionType":1,
      "ConnectedWireIndex":3,
      "ConnectedWireSegmentIndex":0,
      "Points":[{"x":-6.99212,"y":1.4492},{"x":0.0,"y":0.0}]
    },
    {
      "SourcePinAddress":{
        "PinID":855358909,
        "PinOwnerID":605526266
      },
      "TargetPinAddress":{
        "PinID":1799399034,
        "PinOwnerID":949796810
      },
      "ConnectionType":0,
      "ConnectedWireIndex":-1,
      "ConnectedWireSegmentIndex":-1,
      "Points":[{"x":0.0,"y":0.0},{"x":0.0,"y":0.0}]
    },
    {
      "SourcePinAddress":{
        "PinID":1562396775,
        "PinOwnerID":949796810
      },
      "TargetPinAddress":{
        "PinID":0,
        "PinOwnerID":200910699
      },
      "ConnectionType":0,
      "ConnectedWireIndex":-1,
      "ConnectedWireSegmentIndex":-1,
      "Points":[{"x":0.0,"y":0.0},{"x":0.0,"y":0.0}]
    },
    {
      "SourcePinAddress":{
        "PinID":1562396775,
        "PinOwnerID":949796810
      },
      "TargetPinAddress":{
        "PinID":1088781850,
        "PinOwnerID":200770344
      },
      "ConnectionType":1,
      "ConnectedWireIndex":10,
      "ConnectedWireSegmentIndex":0,
      "Points":[{"x":0.85866,"y":4.56407},{"x":0.06057,"y":5.99738},{"x":-8.65298,"y":5.58186},{"x":-8.77519,"y":3.19877},{"x":0.0,"y":0.0}]
    }
  ],
  "Displays": null
}