{
  "DLSVersion": "2.1.6",
  "Name": "CU",
  "NameLocation": 0,
  "ChipType": 0,
  "Size": {
    "x": 0.425,
    "y": 1.125
  },
  "Colour": {
    "r": 0.9525726,
    "g": 0.5187608,
    "b": 0.818085551,
    "a": 1
  },
  "InputPins":[
    {
      "Name":"Instruction",
      "ID":1363699584,
      "Position":{
        "x":-8.65404,
        "y":-2.74438
      },
      "BitCount":4,
      "Colour":0,
      "ValueDisplayMode":0
    },
    {
      "Name":"Fetch Op",
      "ID":2147287271,
      "Position":{
        "x":-8.76906,
        "y":-3.72593
      },
      "BitCount":1,
      "Colour":0,
      "ValueDisplayMode":0
    },
    {
      "Name":"Clock",
      "ID":664344943,
      "Position":{
        "x":-8.79207,
        "y":-5.22125
      },
      "BitCount":1,
      "Colour":0,
      "ValueDisplayMode":0
    },
    {
      "Name":"Clear",
      "ID":746573674,
      "Position":{
        "x":-8.79533,
        "y":-6.97892
      },
      "BitCount":1,
      "Colour":0,
      "ValueDisplayMode":0
    }
  ],
  "OutputPins":[
    {
      "Name":"OUT",
      "ID":1658115924,
      "Position":{
        "x":21.88002,
        "y":-3.70942
      },
      "BitCount":1,
      "Colour":0,
      "ValueDisplayMode":0
    },
    {
      "Name":"OP complete",
      "ID":555270654,
      "Position":{
        "x":23.12731,
        "y":-5.09531
      },
      "BitCount":1,
      "Colour":0,
      "ValueDisplayMode":0
    },
    {
      "Name":"Read Adder",
      "ID":616608962,
      "Position":{
        "x":20.0996,
        "y":-8.34749
      },
      "BitCount":1,
      "Colour":0,
      "ValueDisplayMode":0
    },
    {
      "Name":"Read Bitshift",
      "ID":667133450,
      "Position":{
        "x":20.0996,
        "y":-8.86249
      },
      "BitCount":1,
      "Colour":0,
      "ValueDisplayMode":0
    }
  ],
  "SubChips":[
    {
      "Name":"4-16 Decoder",
      "ID":1467827063,
      "Label":"",
      "Position":{
        "x":-2.76307,
        "y":-2.75259
      },
      "OutputPinColourInfo":[{"PinColour":0,"PinID":922618666},{"PinColour":0,"PinID":591728190}],
      "InternalData":null
    },
    {
      "Name":"8-1BIT",
      "ID":1867378426,
      "Label":"",
      "Position":{
        "x":3.33527,
        "y":-1.84719
      },
      "OutputPinColourInfo":[{"PinColour":0,"PinID":1},{"PinColour":0,"PinID":2},{"PinColour":0,"PinID":3},{"PinColour":0,"PinID":4},{"PinColour":0,"PinID":5},{"PinColour":0,"PinID":6},{"PinColour":0,"PinID":7},{"PinColour":0,"PinID":8}],
      "InternalData":null
    },
    {
      "Name":"8-1BIT",
      "ID":1776926357,
      "Label":"",
      "Position":{
        "x":3.33527,
        "y":-3.97719
      },
      "OutputPinColourInfo":[{"PinColour":0,"PinID":1},{"PinColour":0,"PinID":2},{"PinColour":0,"PinID":3},{"PinColour":0,"PinID":4},{"PinColour":0,"PinID":5},{"PinColour":0,"PinID":6},{"PinColour":0,"PinID":7},{"PinColour":0,"PinID":8}],
      "InternalData":null
    },
    {
      "Name":"4 cycle clock",
      "ID":927015669,
      "Label":"",
      "Position":{
        "x":4.45611,
        "y":-7.10814
      },
      "OutputPinColourInfo":[{"PinColour":0,"PinID":585623528},{"PinColour":0,"PinID":1822958297},{"PinColour":0,"PinID":1982813351},{"PinColour":0,"PinID":1053617233}],
      "InternalData":null
    },
    {
      "Name":"OR",
      "ID":1627935184,
      "Label":"",
      "Position":{
        "x":7.63947,
        "y":0.38399
      },
      "OutputPinColourInfo":[{"PinColour":0,"PinID":281615327}],
      "InternalData":null
    },
    {
      "Name":"OR",
      "ID":1731501597,
      "Label":"",
      "Position":{
        "x":7.73595,
        "y":-4.09233
      },
      "OutputPinColourInfo":[{"PinColour":0,"PinID":281615327}],
      "InternalData":null
    },
    {
      "Name":"OR",
      "ID":247305950,
      "Label":"",
      "Position":{
        "x":7.73595,
        "y":-4.72233
      },
      "OutputPinColourInfo":[{"PinColour":0,"PinID":281615327}],
      "InternalData":null
    },
    {
      "Name":"AND",
      "ID":795269001,
      "Label":"",
      "Position":{
        "x":15.45141,
        "y":-3.28496
      },
      "OutputPinColourInfo":[{"PinColour":0,"PinID":1608085393}],
      "InternalData":null
    },
    {
      "Name":"AND",
      "ID":466782437,
      "Label":"",
      "Position":{
        "x":15.50767,
        "y":-4.02044
      },
      "OutputPinColourInfo":[{"PinColour":0,"PinID":1608085393}],
      "InternalData":null
    },
    {
      "Name":"AND",
      "ID":1764995592,
      "Label":"",
      "Position":{
        "x":15.50767,
        "y":-4.65044
      },
      "OutputPinColourInfo":[{"PinColour":0,"PinID":1608085393}],
      "InternalData":null
    },
    {
      "Name":"AND",
      "ID":610661923,
      "Label":"",
      "Position":{
        "x":15.50767,
        "y":-5.28044
      },
      "OutputPinColourInfo":[{"PinColour":0,"PinID":1608085393}],
      "InternalData":null
    },
    {
      "Name":"4 bit Register",
      "ID":1637506553,
      "Label":"",
      "Position":{
        "x":-4.70965,
        "y":-2.72133
      },
      "OutputPinColourInfo":[{"PinColour":0,"PinID":1009141092}],
      "InternalData":null
    },
    {
      "Name":"OR",
      "ID":2146337389,
      "Label":"",
      "Position":{
        "x":-1.98749,
        "y":-7.54011
      },
      "OutputPinColourInfo":[{"PinColour":0,"PinID":281615327}],
      "InternalData":null
    },
    {
      "Name":"4-OR",
      "ID":886898819,
      "Label":"",
      "Position":{
        "x":7.64725,
        "y":-2.86881
      },
      "OutputPinColourInfo":[{"PinColour":0,"PinID":83017204}],
      "InternalData":null
    },
    {
      "Name":"4-OR",
      "ID":1116449656,
      "Label":"",
      "Position":{
        "x":7.60305,
        "y":-1.69198
      },
      "OutputPinColourInfo":[{"PinColour":0,"PinID":83017204}],
      "InternalData":null
    },
    {
      "Name":"4-OR",
      "ID":2085889667,
      "Label":"",
      "Position":{
        "x":10.17771,
        "y":-1.87431
      },
      "OutputPinColourInfo":[{"PinColour":0,"PinID":83017204}],
      "InternalData":null
    },
    {
      "Name":"4-OR",
      "ID":1150559357,
      "Label":"",
      "Position":{
        "x":17.37329,
        "y":-4.33495
      },
      "OutputPinColourInfo":[{"PinColour":0,"PinID":83017204}],
      "InternalData":null
    },
    {
      "Name":"ALU",
      "ID":728829141,
      "Label":"",
      "Position":{
        "x":21.18307,
        "y":-12.89526
      },
      "OutputPinColourInfo":[{"PinColour":0,"PinID":949089854},{"PinColour":0,"PinID":1558047518},{"PinColour":0,"PinID":779742649},{"PinColour":0,"PinID":891805594}],
      "InternalData":null
    }
  ],
  "Wires":[
    {
      "SourcePinAddress":{
        "PinID":0,
        "PinOwnerID":664344943
      },
      "TargetPinAddress":{
        "PinID":923481592,
        "PinOwnerID":927015669
      },
      "ConnectionType":0,
      "ConnectedWireIndex":-1,
      "ConnectedWireSegmentIndex":-1,
      "Points":[{"x":0.0,"y":0.0},{"x":0.0,"y":0.0}]
    },
    {
      "SourcePinAddress":{
        "PinID":8,
        "PinOwnerID":1776926357
      },
      "TargetPinAddress":{
        "PinID":2143560807,
        "PinOwnerID":247305950
      },
      "ConnectionType":0,
      "ConnectedWireIndex":-1,
      "ConnectedWireSegmentIndex":-1,
      "Points":[{"x":0.0,"y":0.0},{"x":0.0,"y":0.0}]
    },
    {
      "SourcePinAddress":{
        "PinID":7,
        "PinOwnerID":1776926357
      },
      "TargetPinAddress":{
        "PinID":390848654,
        "PinOwnerID":247305950
      },
      "ConnectionType":0,
      "ConnectedWireIndex":-1,
      "ConnectedWireSegmentIndex":-1,
      "Points":[{"x":0.0,"y":0.0},{"x":0.0,"y":0.0}]
    },
    {
      "SourcePinAddress":{
        "PinID":5,
        "PinOwnerID":1776926357
      },
      "TargetPinAddress":{
        "PinID":2143560807,
        "PinOwnerID":1731501597
      },
      "ConnectionType":0,
      "ConnectedWireIndex":-1,
      "ConnectedWireSegmentIndex":-1,
      "Points":[{"x":0.0,"y":0.0},{"x":0.0,"y":0.0}]
    },
    {
      "SourcePinAddress":{
        "PinID":4,
        "PinOwnerID":1776926357
      },
      "TargetPinAddress":{
        "PinID":390848654,
        "PinOwnerID":1731501597
      },
      "ConnectionType":0,
      "ConnectedWireIndex":-1,
      "ConnectedWireSegmentIndex":-1,
      "Points":[{"x":0.0,"y":0.0},{"x":0.0,"y":0.0}]
    },
    {
      "SourcePinAddress":{
        "PinID":1,
        "PinOwnerID":1867378426
      },
      "TargetPinAddress":{
        "PinID":390848654,
        "PinOwnerID":1627935184
      },
      "ConnectionType":0,
      "ConnectedWireIndex":-1,
      "ConnectedWireSegmentIndex":-1,
      "Points":[{"x":0.0,"y":0.0},{"x":0.0,"y":0.0}]
    },
    {
      "SourcePinAddress":{
        "PinID":281615327,
        "PinOwnerID":247305950
      },
      "TargetPinAddress":{
        "PinID":1116305131,
        "PinOwnerID":610661923
      },
      "ConnectionType":0,
      "ConnectedWireIndex":-1,
      "ConnectedWireSegmentIndex":-1,
      "Points":[{"x":0.0,"y":0.0},{"x":0.0,"y":0.0}]
    },
    {
      "SourcePinAddress":{
        "PinID":585623528,
        "PinOwnerID":927015669
      },
      "TargetPinAddress":{
        "PinID":2045518037,
        "PinOwnerID":610661923
      },
      "ConnectionType":0,
      "ConnectedWireIndex":-1,
      "ConnectedWireSegmentIndex":-1,
      "Points":[{"x":0.0,"y":0.0},{"x":0.0,"y":0.0}]
    },
    {
      "SourcePinAddress":{
        "PinID":1822958297,
        "PinOwnerID":927015669
      },
      "TargetPinAddress":{
        "PinID":2045518037,
        "PinOwnerID":1764995592
      },
      "ConnectionType":0,
      "ConnectedWireIndex":-1,
      "ConnectedWireSegmentIndex":-1,
      "Points":[{"x":0.0,"y":0.0},{"x":0.0,"y":0.0}]
    },
    {
      "SourcePinAddress":{
        "PinID":1982813351,
        "PinOwnerID":927015669
      },
      "TargetPinAddress":{
        "PinID":2045518037,
        "PinOwnerID":466782437
      },
      "ConnectionType":0,
      "ConnectedWireIndex":-1,
      "ConnectedWireSegmentIndex":-1,
      "Points":[{"x":0.0,"y":0.0},{"x":0.0,"y":0.0}]
    },
    {
      "SourcePinAddress":{
        "PinID":1053617233,
        "PinOwnerID":927015669
      },
      "TargetPinAddress":{
        "PinID":2045518037,
        "PinOwnerID":795269001
      },
      "ConnectionType":0,
      "ConnectedWireIndex":-1,
      "ConnectedWireSegmentIndex":-1,
      "Points":[{"x":0.0,"y":0.0},{"x":0.0,"y":0.0}]
    },
    {
      "SourcePinAddress":{
        "PinID":281615327,
        "PinOwnerID":1731501597
      },
      "TargetPinAddress":{
        "PinID":1116305131,
        "PinOwnerID":1764995592
      },
      "ConnectionType":0,
      "ConnectedWireIndex":-1,
      "ConnectedWireSegmentIndex":-1,
      "Points":[{"x":0.0,"y":0.0},{"x":0.0,"y":0.0}]
    },
    {
      "SourcePinAddress":{
        "PinID":281615327,
        "PinOwnerID":1627935184
      },
      "TargetPinAddress":{
        "PinID":1116305131,
        "PinOwnerID":795269001
      },
      "ConnectionType":0,
      "ConnectedWireIndex":-1,
      "ConnectedWireSegmentIndex":-1,
      "Points":[{"x":0.0,"y":0.0},{"x":0.0,"y":0.0}]
    },
    {
      "SourcePinAddress":{
        "PinID":0,
        "PinOwnerID":1363699584
      },
      "TargetPinAddress":{
        "PinID":1142201962,
        "PinOwnerID":1637506553
      },
      "ConnectionType":0,
      "ConnectedWireIndex":-1,
      "ConnectedWireSegmentIndex":-1,
      "Points":[{"x":0.0,"y":0.0},{"x":0.0,"y":0.0}]
    },
    {
      "SourcePinAddress":{
        "PinID":1009141092,
        "PinOwnerID":1637506553
      },
      "TargetPinAddress":{
        "PinID":1326797098,
        "PinOwnerID":1467827063
      },
      "ConnectionType":0,
      "ConnectedWireIndex":-1,
      "ConnectedWireSegmentIndex":-1,
      "Points":[{"x":0.0,"y":0.0},{"x":0.0,"y":0.0}]
    },
    {
      "SourcePinAddress":{
        "PinID":0,
        "PinOwnerID":664344943
      },
      "TargetPinAddress":{
        "PinID":1566236010,
        "PinOwnerID":1637506553
      },
      "ConnectionType":0,
      "ConnectedWireIndex":-1,
      "ConnectedWireSegmentIndex":-1,
      "Points":[{"x":0.0,"y":0.0},{"x":0.0,"y":0.0}]
    },
    {
      "SourcePinAddress":{
        "PinID":0,
        "PinOwnerID":2147287271
      },
      "TargetPinAddress":{
        "PinID":2107518268,
        "PinOwnerID":1637506553
      },
      "ConnectionType":0,
      "ConnectedWireIndex":-1,
      "ConnectedWireSegmentIndex":-1,
      "Points":[{"x":0.0,"y":0.0},{"x":0.0,"y":0.0}]
    },
    {
      "SourcePinAddress":{
        "PinID":922618666,
        "PinOwnerID":1467827063
      },
      "TargetPinAddress":{
        "PinID":0,
        "PinOwnerID":1867378426
      },
      "ConnectionType":0,
      "ConnectedWireIndex":-1,
      "ConnectedWireSegmentIndex":-1,
      "Points":[{"x":0.0,"y":0.0},{"x":0.0,"y":0.0}]
    },
    {
      "SourcePinAddress":{
        "PinID":591728190,
        "PinOwnerID":1467827063
      },
      "TargetPinAddress":{
        "PinID":0,
        "PinOwnerID":1776926357
      },
      "ConnectionType":0,
      "ConnectedWireIndex":-1,
      "ConnectedWireSegmentIndex":-1,
      "Points":[{"x":0.0,"y":0.0},{"x":0.0,"y":0.0}]
    },
    {
      "SourcePinAddress":{
        "PinID":0,
        "PinOwnerID":2147287271
      },
      "TargetPinAddress":{
        "PinID":1530121655,
        "PinOwnerID":927015669
      },
      "ConnectionType":0,
      "ConnectedWireIndex":-1,
      "ConnectedWireSegmentIndex":-1,
      "Points":[{"x":0.0,"y":0.0},{"x":0.0,"y":0.0}]
    },
    {
      "SourcePinAddress":{
        "PinID":0,
        "PinOwnerID":746573674
      },
      "TargetPinAddress":{
        "PinID":390848654,
        "PinOwnerID":2146337389
      },
      "ConnectionType":0,
      "ConnectedWireIndex":-1,
      "ConnectedWireSegmentIndex":-1,
      "Points":[{"x":0.0,"y":0.0},{"x":0.0,"y":0.0}]
    },
    {
      "SourcePinAddress":{
        "PinID":281615327,
        "PinOwnerID":2146337389
      },
      "TargetPinAddress":{
        "PinID":342996747,
        "PinOwnerID":927015669
      },
      "ConnectionType":0,
      "ConnectedWireIndex":-1,
      "ConnectedWireSegmentIndex":-1,
      "Points":[{"x":0.0,"y":0.0},{"x":0.0,"y":0.0}]
    },
    {
      "SourcePinAddress":{
        "PinID":281615327,
        "PinOwnerID":2146337389
      },
      "TargetPinAddress":{
        "PinID":991952778,
        "PinOwnerID":1637506553
      },
      "ConnectionType":1,
      "ConnectedWireIndex":21,
      "ConnectedWireSegmentIndex":0,
      "Points":[{"x":-0.97454,"y":-7.55073},{"x":-5.84911,"y":-3.68761},{"x":0.0,"y":0.0}]
    },
    {
      "SourcePinAddress":{
        "PinID":3,
        "PinOwnerID":1776926357
      },
      "TargetPinAddress":{
        "PinID":1696577128,
        "PinOwnerID":886898819
      },
      "ConnectionType":0,
      "ConnectedWireIndex":-1,
      "ConnectedWireSegmentIndex":-1,
      "Points":[{"x":0.0,"y":0.0},{"x":0.0,"y":0.0}]
    },
    {
      "SourcePinAddress":{
        "PinID":2,
        "PinOwnerID":1776926357
      },
      "TargetPinAddress":{
        "PinID":82060659,
        "PinOwnerID":886898819
      },
      "ConnectionType":0,
      "ConnectedWireIndex":-1,
      "ConnectedWireSegmentIndex":-1,
      "Points":[{"x":0.0,"y":0.0},{"x":0.0,"y":0.0}]
    },
    {
      "SourcePinAddress":{
        "PinID":1,
        "PinOwnerID":1776926357
      },
      "TargetPinAddress":{
        "PinID":2095861843,
        "PinOwnerID":886898819
      },
      "ConnectionType":0,
      "ConnectedWireIndex":-1,
      "ConnectedWireSegmentIndex":-1,
      "Points":[{"x":0.0,"y":0.0},{"x":0.0,"y":0.0}]
    },
    {
      "SourcePinAddress":{
        "PinID":8,
        "PinOwnerID":1867378426
      },
      "TargetPinAddress":{
        "PinID":1896790319,
        "PinOwnerID":886898819
      },
      "ConnectionType":0,
      "ConnectedWireIndex":-1,
      "ConnectedWireSegmentIndex":-1,
      "Points":[{"x":0.0,"y":0.0},{"x":0.0,"y":0.0}]
    },
    {
      "SourcePinAddress":{
        "PinID":7,
        "PinOwnerID":1867378426
      },
      "TargetPinAddress":{
        "PinID":1696577128,
        "PinOwnerID":1116449656
      },
      "ConnectionType":0,
      "ConnectedWireIndex":-1,
      "ConnectedWireSegmentIndex":-1,
      "Points":[{"x":0.0,"y":0.0},{"x":0.0,"y":0.0}]
    },
    {
      "SourcePinAddress":{
        "PinID":6,
        "PinOwnerID":1867378426
      },
      "TargetPinAddress":{
        "PinID":82060659,
        "PinOwnerID":1116449656
      },
      "ConnectionType":0,
      "ConnectedWireIndex":-1,
      "ConnectedWireSegmentIndex":-1,
      "Points":[{"x":0.0,"y":0.0},{"x":0.0,"y":0.0}]
    },
    {
      "SourcePinAddress":{
        "PinID":5,
        "PinOwnerID":1867378426
      },
      "TargetPinAddress":{
        "PinID":2095861843,
        "PinOwnerID":1116449656
      },
      "ConnectionType":0,
      "ConnectedWireIndex":-1,
      "ConnectedWireSegmentIndex":-1,
      "Points":[{"x":0.0,"y":0.0},{"x":0.0,"y":0.0}]
    },
    {
      "SourcePinAddress":{
        "PinID":4,
        "PinOwnerID":1867378426
      },
      "TargetPinAddress":{
        "PinID":1896790319,
        "PinOwnerID":1116449656
      },
      "ConnectionType":0,
      "ConnectedWireIndex":-1,
      "ConnectedWireSegmentIndex":-1,
      "Points":[{"x":0.0,"y":0.0},{"x":0.0,"y":0.0}]
    },
    {
      "SourcePinAddress":{
        "PinID":83017204,
        "PinOwnerID":886898819
      },
      "TargetPinAddress":{
        "PinID":1696577128,
        "PinOwnerID":2085889667
      },
      "ConnectionType":0,
      "ConnectedWireIndex":-1,
      "ConnectedWireSegmentIndex":-1,
      "Points":[{"x":0.0,"y":0.0},{"x":0.0,"y":0.0}]
    },
    {
      "SourcePinAddress":{
        "PinID":83017204,
        "PinOwnerID":1116449656
      },
      "TargetPinAddress":{
        "PinID":82060659,
        "PinOwnerID":2085889667
      },
      "ConnectionType":0,
      "ConnectedWireIndex":-1,
      "ConnectedWireSegmentIndex":-1,
      "Points":[{"x":0.0,"y":0.0},{"x":0.0,"y":0.0}]
    },
    {
      "SourcePinAddress":{
        "PinID":3,
        "PinOwnerID":1867378426
      },
      "TargetPinAddress":{
        "PinID":2095861843,
        "PinOwnerID":2085889667
      },
      "ConnectionType":0,
      "ConnectedWireIndex":-1,
      "ConnectedWireSegmentIndex":-1,
      "Points":[{"x":0.0,"y":0.0},{"x":6.86822,"y":-1.00688},{"x":8.00637,"y":-0.9461},{"x":0.0,"y":0.0}]
    },
    {
      "SourcePinAddress":{
        "PinID":83017204,
        "PinOwnerID":2085889667
      },
      "TargetPinAddress":{
        "PinID":1116305131,
        "PinOwnerID":466782437
      },
      "ConnectionType":0,
      "ConnectedWireIndex":-1,
      "ConnectedWireSegmentIndex":-1,
      "Points":[{"x":0.0,"y":0.0},{"x":0.0,"y":0.0}]
    },
    {
      "SourcePinAddress":{
        "PinID":1608085393,
        "PinOwnerID":795269001
      },
      "TargetPinAddress":{
        "PinID":1896790319,
        "PinOwnerID":1150559357
      },
      "ConnectionType":0,
      "ConnectedWireIndex":-1,
      "ConnectedWireSegmentIndex":-1,
      "Points":[{"x":0.0,"y":0.0},{"x":0.0,"y":0.0}]
    },
    {
      "SourcePinAddress":{
        "PinID":1608085393,
        "PinOwnerID":466782437
      },
      "TargetPinAddress":{
        "PinID":2095861843,
        "PinOwnerID":1150559357
      },
      "ConnectionType":0,
      "ConnectedWireIndex":-1,
      "ConnectedWireSegmentIndex":-1,
      "Points":[{"x":0.0,"y":0.0},{"x":0.0,"y":0.0}]
    },
    {
      "SourcePinAddress":{
        "PinID":1608085393,
        "PinOwnerID":1764995592
      },
      "TargetPinAddress":{
        "PinID":82060659,
        "PinOwnerID":1150559357
      },
      "ConnectionType":0,
      "ConnectedWireIndex":-1,
      "ConnectedWireSegmentIndex":-1,
      "Points":[{"x":0.0,"y":0.0},{"x":0.0,"y":0.0}]
    },
    {
      "SourcePinAddress":{
        "PinID":1608085393,
        "PinOwnerID":610661923
      },
      "TargetPinAddress":{
        "PinID":1696577128,
        "PinOwnerID":1150559357
      },
      "ConnectionType":0,
      "ConnectedWireIndex":-1,
      "ConnectedWireSegmentIndex":-1,
      "Points":[{"x":0.0,"y":0.0},{"x":0.0,"y":0.0}]
    },
    {
      "SourcePinAddress":{
        "PinID":83017204,
        "PinOwnerID":1150559357
      },
      "TargetPinAddress":{
        "PinID":0,
        "PinOwnerID":555270654
      },
      "ConnectionType":0,
      "ConnectedWireIndex":-1,
      "ConnectedWireSegmentIndex":-1,
      "Points":[{"x":0.0,"y":0.0},{"x":0.0,"y":0.0}]
    }
  ],
  "Displays": null
}